<mvc:View controllerName="com.aml.amlui07.controller.View1"
    xmlns:mvc="sap.ui.core.mvc"
    xmlns="sap.m"
    xmlns:l="sap.ui.layout"
    xmlns:f="sap.ui.layout.form"
    xmlns:core="sap.ui.core">

    <Page id="page" showHeader="true">
        <customHeader>
            <Bar>
                <contentMiddle>
                    <Title text="Component Change and Service Forecast" level="H1" class="myPageTitle"/>
                </contentMiddle>
            </Bar>
        </customHeader>

        <content>
            <Panel headerText="Search Details" expandable="true" expanded="true">
                <f:SimpleForm editable="true" layout="ResponsiveGridLayout" labelSpanL="2" labelSpanM="2"
                              emptySpanL="6" emptySpanM="6">
                    <f:content>

                        <!-- Maint Plant From-To -->
                        <Label text="Maint Plant"/>
                        <HBox>
                            <Input id="idPlantFrom" placeholder="From" width="150px"/>
                            <Text text="To" class="sapUiSmallMarginBegin sapUiSmallMarginEnd"/>
                            <Input id="idPlantTo" placeholder="To" width="150px"/>
                            <Button icon="sap-icon://journey-arrive" tooltip="Search" class="sapUiSmallMarginBegin"/>
                        </HBox>

                        <!-- Plant Section From-To -->
                        <Label text="Plant Section"/>
                        <HBox>
                            <Input id="idSectionFrom" placeholder="From" width="150px"/>
                            <Text text="To" class="sapUiSmallMarginBegin sapUiSmallMarginEnd"/>
                            <Input id="idSectionTo" placeholder="To" width="150px"/>
                            <Button icon="sap-icon://journey-arrive" tooltip="Search" class="sapUiSmallMarginBegin"/>
                        </HBox>

                        <!-- Location From-To -->
                        <Label text="Location"/>
                        <HBox>
                            <Input id="idLocationFrom" placeholder="From" width="150px"/>
                            <Text text="To" class="sapUiSmallMarginBegin sapUiSmallMarginEnd"/>
                            <Input id="idLocationTo" placeholder="To" width="150px"/>
                            <Button icon="sap-icon://journey-arrive" tooltip="Search" class="sapUiSmallMarginBegin"/>
                        </HBox>

                        <!-- Planner Group From-To -->
                        <Label text="Planner Group"/>
                        <HBox>
                            <Input id="idPlannerGroupFrom" placeholder="From" width="150px"/>
                            <Text text="To" class="sapUiSmallMarginBegin sapUiSmallMarginEnd"/>
                            <Input id="idPlannerGroupTo" placeholder="To" width="150px"/>
                            <Button icon="sap-icon://journey-arrive" tooltip="Search" class="sapUiSmallMarginBegin"/>
                        </HBox>

                        <!-- Equipment From-To -->
                        <Label text="Equipment"/>
                        <HBox>
                            <Input id="idEquipmentFrom" placeholder="From" width="150px"/>
                            <Text text="To" class="sapUiSmallMarginBegin sapUiSmallMarginEnd"/>
                            <Input id="idEquipmentTo" placeholder="To" width="150px"/>
                            <Button icon="sap-icon://journey-arrive" tooltip="Search" class="sapUiSmallMarginBegin"/>
                        </HBox>

                        <!-- Buttons aligned right -->
                        <Label text=""/>
                        <FlexBox justifyContent="End">
                            <Button icon="sap-icon://accept" text="Go" type="Accept" class="sapUiTinyMarginEnd"/>
                            <Button icon="sap-icon://reset" text="Reset" type="Reject"/>
                        </FlexBox>

                    </f:content>
                </f:SimpleForm>
            </Panel>

            <!-- Scrollable Table -->
            <ScrollContainer width="100%" height="auto" horizontal="true" vertical="false">
                <Table items="{pm>/PMData}" growing="true" growingScrollToLoad="true" width="auto" class="sapUiResponsiveMargin" inset="false">
                    <columns>
                        <Column><Text text="Maint Plant"/></Column>
                        <Column><Text text="Plant Section"/></Column>
                        <Column><Text text="Location"/></Column>
                        <Column><Text text="Planner Group"/></Column>
                        <Column><Text text="Maint Order Number"/></Column>
                        <Column><Text text="Created By"/></Column>
                        <Column><Text text="Created On"/></Column>
                        <Column><Text text="Basic Start Date"/></Column>
                        <Column><Text text="Material No."/></Column>
                        <Column><Text text="Material Description"/></Column>
                        <Column><Text text="Required Quantity"/></Column>
                        <Column><Text text="Requirement Date"/></Column>
                    </columns>
                    <items>
                        <ColumnListItem>
                            <cells>
                                <Text text="{pm>MaintPlant}"/>
                                <Text text="{pm>PlantSection}"/>
                                <Text text="{pm>Location}"/>
                                <Text text="{pm>PlannerGroup}"/>
                                <Text text="{pm>MaintOrderNumber}"/>
                                <Text text="{pm>CreatedBy}"/>
                                <Text text="{pm>CreatedOn}"/>
                                <Text text="{pm>BasicStartDate}"/>
                                <Text text="{pm>MaterialNo}"/>
                                <Text text="{pm>MaterialDescription}"/>
                                <Text text="{pm>RequiredQuantity}"/>
                                <Text text="{pm>RequirementDate}"/>
                            </cells>
                        </ColumnListItem>
                    </items>
                </Table>
            </ScrollContainer>
        </content>
    </Page>
</mvc:View>
